CHANGES.rst
MANIFEST.in
README.rst
VERSION
requirements.txt
setup.cfg
setup.py
test-requirements.txt
aioarangodb/__init__.py
aioarangodb/api.py
aioarangodb/aql.py
aioarangodb/client.py
aioarangodb/cluster.py
aioarangodb/collection.py
aioarangodb/connection.py
aioarangodb/cursor.py
aioarangodb/database.py
aioarangodb/errno.py
aioarangodb/exceptions.py
aioarangodb/executor.py
aioarangodb/formatter.py
aioarangodb/foxx.py
aioarangodb/graph.py
aioarangodb/http.py
aioarangodb/job.py
aioarangodb/pregel.py
aioarangodb/replication.py
aioarangodb/request.py
aioarangodb/resolver.py
aioarangodb/response.py
aioarangodb/utils.py
aioarangodb/version.py
aioarangodb/wal.py
aioarangodb.egg-info/PKG-INFO
aioarangodb.egg-info/SOURCES.txt
aioarangodb.egg-info/dependency_links.txt
aioarangodb.egg-info/not-zip-safe
aioarangodb.egg-info/requires.txt
aioarangodb.egg-info/top_level.txt
aioarangodb/tests/__init__.py
aioarangodb/tests/arangodocker.py
aioarangodb/tests/conftest.py
aioarangodb/tests/executors.py
aioarangodb/tests/fixtures.py
aioarangodb/tests/helpers.py
aioarangodb/tests/test_analyzer.py
aioarangodb/tests/test_aql.py
aioarangodb/tests/test_async.py
aioarangodb/tests/test_auth.py
aioarangodb/tests/test_batch.py
aioarangodb/tests/test_client.py
aioarangodb/tests/test_cluster.py
aioarangodb/tests/test_collection.py
aioarangodb/tests/test_cursor.py
aioarangodb/tests/test_database.py
aioarangodb/tests/test_document.py
aioarangodb/tests/test_exception.py
aioarangodb/tests/test_foxx.py
aioarangodb/tests/test_graph.py
aioarangodb/tests/test_index.py
aioarangodb/tests/test_permission.py
aioarangodb/tests/test_pregel.py
aioarangodb/tests/test_replication.py
aioarangodb/tests/test_request.py
aioarangodb/tests/test_resolver.py
aioarangodb/tests/test_response.py
aioarangodb/tests/test_task.py
aioarangodb/tests/test_transaction.py
aioarangodb/tests/test_user.py
aioarangodb/tests/test_view.py
aioarangodb/tests/test_wal.py