Metadata-Version: 1.1
Name: aioarangodb
Version: 0.1.2
Summary: AsyncIO ArangoDB driver
Home-page: http://github.com/bloodbare/aioarangodb
Author: Ramon Navarro
Author-email: ramon.nb@gmail.com
License: MIT
Platform: UNKNOWN
Classifier: Development Status :: 2 - Pre-Alpha
Classifier: Intended Audience :: Developers
Classifier: Programming Language :: Python :: 3.5
Classifier: Programming Language :: Python :: 3.6
Classifier: Programming Language :: Python :: 3.7
Classifier: Programming Language :: Python :: 3.8
